{
    "layers": [
        {
            "score": 0,
            "miss": 0,
            "scorestogo": 0,
            "conflicts": 0,
            "done": 228,
            "togo": 0,
            "cpu": 2030,
            "time": 1722,
            "certtime": 0,
            "news": 0,
            "wrong": 0
        },
        {
            "score": 0,
            "miss": 0,
            "scorestogo": 0,
            "conflicts": 0,
            "done": 152,
            "togo": 0,
            "cpu": 1899,
            "time": 1498,
            "certtime": 0,
            "news": 0,
            "wrong": 0
        }
    ],
    "participants": {
        "228208": {
            "score": 67,
            "miss": 9,
            "scorestogo": 0,
            "conflicts": 0,
            "done": 76,
            "togo": 0,
            "cpu": 1185,
            "time": 812,
            "certtime": 0,
            "news": 0,
            "wrong": 0,
            "layer": 0,
            "solver": "AProVE 007659f",
            "solver id": "12921",
            "configuration": "standard",
            "CERTIFIED YES": 0,
            "CERTIFIED NO": 0,
            "CERTIFIED UP": 0,
            "CERTIFIED LOW": 0,
            "YES": 65,
            "SAST": 0,
            "PAST": 0,
            "AST": 0,
            "NO": 2,
            "UP": 0,
            "LOW": 0,
            "MAYBE": 9,
            "timeout": 0,
            "error": 0,
            "normalized": 1
        },
        "228408": {
            "score": 48,
            "miss": 28,
            "scorestogo": 0,
            "conflicts": 0,
            "done": 76,
            "togo": 0,
            "cpu": 64,
            "time": 57,
            "certtime": 0,
            "news": 0,
            "wrong": 0,
            "layer": 0,
            "solver": "NaTT",
            "solver id": "12933",
            "configuration": "Default",
            "CERTIFIED YES": 0,
            "CERTIFIED NO": 0,
            "CERTIFIED UP": 0,
            "CERTIFIED LOW": 0,
            "YES": 47,
            "SAST": 0,
            "PAST": 0,
            "AST": 0,
            "NO": 1,
            "UP": 0,
            "LOW": 0,
            "MAYBE": 28,
            "timeout": 0,
            "error": 0,
            "normalized": 0.7164179104477612
        },
        "163986": {
            "score": 64,
            "miss": 12,
            "scorestogo": 0,
            "conflicts": 0,
            "done": 76,
            "togo": 0,
            "cpu": 781,
            "time": 853,
            "certtime": 0,
            "news": 0,
            "wrong": 0,
            "layer": 0,
            "solver": "muterm 5.18",
            "solver id": "9061",
            "configuration": "default",
            "CERTIFIED YES": 0,
            "CERTIFIED NO": 0,
            "CERTIFIED UP": 0,
            "CERTIFIED LOW": 0,
            "YES": 64,
            "SAST": 0,
            "PAST": 0,
            "AST": 0,
            "NO": 0,
            "UP": 0,
            "LOW": 0,
            "MAYBE": 12,
            "timeout": 0,
            "error": 0,
            "normalized": 0.9552238805970149
        },
        "228209": {
            "score": 64,
            "miss": 12,
            "scorestogo": 0,
            "conflicts": 0,
            "done": 76,
            "togo": 0,
            "cpu": 1864,
            "time": 1463,
            "certtime": 1.1,
            "news": 0,
            "wrong": 0,
            "layer": 1,
            "solver": "AProVE 007659f",
            "solver id": "12921",
            "configuration": "certified",
            "CERTIFIED YES": 64,
            "CERTIFIED NO": 0,
            "CERTIFIED UP": 0,
            "CERTIFIED LOW": 0,
            "YES": 0,
            "SAST": 0,
            "PAST": 0,
            "AST": 0,
            "NO": 0,
            "UP": 0,
            "LOW": 0,
            "MAYBE": 12,
            "timeout": 0,
            "error": 0,
            "normalized": 0.9552238805970149
        },
        "228409": {
            "score": 26,
            "miss": 50,
            "scorestogo": 0,
            "conflicts": 0,
            "done": 76,
            "togo": 0,
            "cpu": 35,
            "time": 35,
            "certtime": 0,
            "news": 0,
            "wrong": 0,
            "layer": 1,
            "solver": "NaTT",
            "solver id": "12933",
            "configuration": "Certified_AC",
            "CERTIFIED YES": 26,
            "CERTIFIED NO": 0,
            "CERTIFIED UP": 0,
            "CERTIFIED LOW": 0,
            "YES": 0,
            "SAST": 0,
            "PAST": 0,
            "AST": 0,
            "NO": 0,
            "UP": 0,
            "LOW": 0,
            "MAYBE": 47,
            "timeout": 0,
            "error": 0,
            "normalized": 0.3880597014925373
        }
    },
    "conflicting": false
}