{"all":{"done":7535,"togo":0,"cpu":1209288,"time":614325,"scorestogo":0},"participants":{"360349":{"solver":"NTI","solver id":"29557","configuration":"default","score":457,"unscored":1050,"scorestogo":0,"conflicts":0,"done":1507,"togo":0,"cpu":651709,"time":300599,"certtime":0,"ranked":true,"TIMEOUT":992,"NO":236,"YES":221,"MAYBE":58},"350520":{"solver":"NaTT v.1.6c","solver id":"27947","configuration":"Default","score":1033,"unscored":474,"scorestogo":0,"conflicts":0,"done":1507,"togo":0,"cpu":10010,"time":9848,"certtime":0,"ranked":true,"MAYBE":453,"YES":864,"NO":169,"TIMEOUT":21},"360055":{"solver":"ttt2-1.20","solver id":"29431","configuration":"ttt2","score":1038,"unscored":469,"scorestogo":0,"conflicts":0,"done":1507,"togo":0,"cpu":174799,"time":51028,"certtime":0,"ranked":true,"MAYBE":464,"YES":835,"NO":203,"TIMEOUT":5},"360174":{"solver":"AProVE","solver id":"29458","configuration":"standard","score":1310,"unscored":197,"scorestogo":0,"conflicts":0,"done":1507,"togo":0,"cpu":172774,"time":66453,"certtime":0,"ranked":true,"NO":278,"TIMEOUT":197,"YES":1032},"326595":{"solver":"muterm 6.0.3","solver id":"22652","configuration":"default","score":850,"unscored":657,"scorestogo":0,"conflicts":0,"done":1507,"togo":0,"cpu":199996,"time":186397,"certtime":0,"ranked":true,"TIMEOUT":557,"YES":716,"MAYBE":100,"NO":134}}}